cryptal/__init__.py
cryptal/cryptal.py
cryptal-0.1.1.dist-info/licenses/LICENSE
cryptal-0.1.1.dist-info/METADATA
cryptal-0.1.1.dist-info/WHEEL
cryptal-0.1.1.dist-info/top_level.txt
cryptal-0.1.1.dist-info/RECORD
